bear_kids_player/Chinese musical instrument full of faint sadness.mpg
bear_kids_player/K-Lite_Codec_Pack_1526_Basic.exe
bear_kids_player/Question_dialog.ui
bear_kids_player/__init__.py
bear_kids_player/bear_kids_player.py
bear_kids_player/bear_kids_player_main.py
bear_kids_player/compile.py
bear_kids_player/config.csv
bear_kids_player/config_processing.py
bear_kids_player/question_database_operation.py
bear_kids_player/questions.csv
bear_kids_player/run_bear_kids_player.py
bear_kids_player/test.py
bear_kids_player-0.1.4.dist-info/METADATA
bear_kids_player-0.1.4.dist-info/WHEEL
bear_kids_player-0.1.4.dist-info/top_level.txt
bear_kids_player-0.1.4.dist-info/RECORD
