Metadata-Version: 2.1
Name: bear-kids-player
Version: 0.1.4
Summary: A player for kids
Home-page: https://github.com/shawnyanwang/bear_kids_player
Author: Shawn Wang
Author-email: shawnyanwang@gmail.com
License: MIT
Platform: UNKNOWN
Classifier: Programming Language :: Python :: 3
Classifier: License :: OSI Approved :: MIT License
Classifier: Operating System :: OS Independent
Requires-Python: >=3.7
Requires-Dist: numpy
Requires-Dist: six
Requires-Dist: pytz
Requires-Dist: pandas
Requires-Dist: PyQt5
Requires-Dist: playsound
Requires-Dist: gtts
